og_up/__init__.py
og_up/kernel_up.py
og_up/model_downloader.py
og_up/up.py
og_up/utils.py
og_up-0.5.3.dist-info/METADATA
og_up-0.5.3.dist-info/WHEEL
og_up-0.5.3.dist-info/entry_points.txt
og_up-0.5.3.dist-info/top_level.txt
og_up-0.5.3.dist-info/RECORD
